{
    "comicName": "咒術回戰",
    "author": "芥見下々 ",
    "state": "連載中",
    "label": [
        "熱血",
        "冒險"
    ],
    "updateTime": "            倒序            連載中                | 共190章, 10月09號                 最新                        第200話 直接會談（1）                                            ",
    "chpaterList": [
        {
            "chapterTitle": "第200話 直接會談（1）                    （4P）                                ",
            "chapterId": "/m252912/"
        },
        {
            "chapterTitle": "第201話 直接會談（2）                    （19P）                                ",
            "chapterId": "/m253961/"
        },
        {
            "chapterTitle": "第199話 綽號                    （8P）                                ",
            "chapterId": "/m251823/"
        },
        {
            "chapterTitle": "第198話 櫻島結界（8）                    （19P）                                ",
            "chapterId": "/m251132/"
        },
        {
            "chapterTitle": "第197話 櫻島結界（7）                    （16P）                                ",
            "chapterId": "/m249134/"
        },
        {
            "chapterTitle": "第196話 櫻島結界（6）                    （16P）                                ",
            "chapterId": "/m247028/"
        },
        {
            "chapterTitle": "第195話 櫻島結界（5）                    （19P）                                ",
            "chapterId": "/m246496/"
        },
        {
            "chapterTitle": "第194話 櫻島結界（4）                    （18P）                                ",
            "chapterId": "/m245703/"
        },
        {
            "chapterTitle": "第193話 櫻島結界（3）                    （16P）                                ",
            "chapterId": "/m243608/"
        },
        {
            "chapterTitle": "第192話 櫻島結界（2）                    （19P）                                ",
            "chapterId": "/m243017/"
        },
        {
            "chapterTitle": "第191話 櫻島結界（1）                    （18P）                                ",
            "chapterId": "/m241154/"
        },
        {
            "chapterTitle": "第190話 東京第2結界（9）                    （19P）                                ",
            "chapterId": "/m240205/"
        },
        {
            "chapterTitle": "第189話 東京第2結界（8）                    （18P）                                ",
            "chapterId": "/m238141/"
        },
        {
            "chapterTitle": "第188話 東京第2結界（7）                    （16P）                                ",
            "chapterId": "/m237261/"
        },
        {
            "chapterTitle": "第187話 東京第2結界（6）                    （17P）                                ",
            "chapterId": "/m236114/"
        },
        {
            "chapterTitle": "第186話 東京第2結界（5）                    （17P）                                ",
            "chapterId": "/m233577/"
        },
        {
            "chapterTitle": "第185話 BYE BYE                    （17P）                                ",
            "chapterId": "/m230988/"
        },
        {
            "chapterTitle": "第184話 試看版                    （19P）                                ",
            "chapterId": "/m230173/"
        },
        {
            "chapterTitle": "第183話 東京第2結界（3）                    （19P）                                ",
            "chapterId": "/m228095/"
        },
        {
            "chapterTitle": "第182話 東京第2結界（2）                    （18P）                                ",
            "chapterId": "/m226258/"
        },
        {
            "chapterTitle": "第181話 東京第2結界（1）                    （22P）                                ",
            "chapterId": "/m225354/"
        },
        {
            "chapterTitle": "第180話 仙臺結界（7）                    （16P）                                ",
            "chapterId": "/m223753/"
        },
        {
            "chapterTitle": "第179話 仙臺結界（6）                    （16P）                                ",
            "chapterId": "/m221738/"
        },
        {
            "chapterTitle": "第178話 仙臺結界（5）                    （16P）                                ",
            "chapterId": "/m220841/"
        },
        {
            "chapterTitle": "第177話 仙臺結界（4）                    （17P）                                ",
            "chapterId": "/m219310/"
        },
        {
            "chapterTitle": "第176話 仙臺結界（3）                    （17P）                                ",
            "chapterId": "/m218426/"
        },
        {
            "chapterTitle": "第175話 仙臺結界（2）                    （19P）                                ",
            "chapterId": "/m217524/"
        },
        {
            "chapterTitle": "第174話 仙臺結界（1）                    （19P）                                ",
            "chapterId": "/m215524/"
        },
        {
            "chapterTitle": "第173話 東京第1結界（13）                    （21P）                                ",
            "chapterId": "/m214727/"
        },
        {
            "chapterTitle": "第172話 東京第1結界（12）                    （18P）                                ",
            "chapterId": "/m213888/"
        },
        {
            "chapterTitle": "第171話 東京第1結界（11）                    （18P）                                ",
            "chapterId": "/m213283/"
        },
        {
            "chapterTitle": "第170話 東京第1結界（10）                    （18P）                                ",
            "chapterId": "/m210788/"
        },
        {
            "chapterTitle": "第169話 試看版                    （21P）                                ",
            "chapterId": "/m209748/"
        },
        {
            "chapterTitle": "劇場版特別短篇                     （9P）                                ",
            "chapterId": "/m208901/"
        },
        {
            "chapterTitle": "第168話 試看版                    （21P）                                ",
            "chapterId": "/m208900/"
        },
        {
            "chapterTitle": "第167話                     （19P）                                ",
            "chapterId": "/m207756/"
        },
        {
            "chapterTitle": "第166話 東京第1結界（6）                    （19P）                                ",
            "chapterId": "/m206429/"
        },
        {
            "chapterTitle": "第165話 東京第1結界（5）                    （19P）                                ",
            "chapterId": "/m205320/"
        },
        {
            "chapterTitle": "第164話                     （19P）                                ",
            "chapterId": "/m204242/"
        },
        {
            "chapterTitle": "第163話                     （18P）                                ",
            "chapterId": "/m204241/"
        },
        {
            "chapterTitle": "第162話 東京結界（2）                    （19P）                                ",
            "chapterId": "/m201796/"
        },
        {
            "chapterTitle": "第161話 東京結界（1）                    （19P）                                ",
            "chapterId": "/m201795/"
        },
        {
            "chapterTitle": "第160話 結界                    （16P）                                ",
            "chapterId": "/m198958/"
        },
        {
            "chapterTitle": "第159話 審判                    （18P）                                ",
            "chapterId": "/m197792/"
        },
        {
            "chapterTitle": "第158話 小金蟲                    （19P）                                ",
            "chapterId": "/m196886/"
        },
        {
            "chapterTitle": "第157話 零件                    （18P）                                ",
            "chapterId": "/m196472/"
        },
        {
            "chapterTitle": "第156話 一閃一閃亮晶晶                    （19P）                                ",
            "chapterId": "/m196471/"
        },
        {
            "chapterTitle": "第155話 熱                    （19P）                                ",
            "chapterId": "/m194315/"
        },
        {
            "chapterTitle": "第154話 潛入                    （19P）                                ",
            "chapterId": "/m192231/"
        },
        {
            "chapterTitle": "第153話 賭博擂合                    （18P）                                ",
            "chapterId": "/m191165/"
        },
        {
            "chapterTitle": "第152話 銜蘆-尾聲-                    （9P）                                ",
            "chapterId": "/m180970/"
        },
        {
            "chapterTitle": "第151話 銜蘆-四-                    （15P）                                ",
            "chapterId": "/m179742/"
        },
        {
            "chapterTitle": "第150話                     （20P）                                ",
            "chapterId": "/m177916/"
        },
        {
            "chapterTitle": "第149話 PERFECT PREPARATION PART2                    （18P）                                ",
            "chapterId": "/m176709/"
        },
        {
            "chapterTitle": "第148話 銜葦                    （5P）                                ",
            "chapterId": "/m175513/"
        },
        {
            "chapterTitle": "第147話 熊貓也會哭                    （4P）                                ",
            "chapterId": "/m172997/"
        },
        {
            "chapterTitle": "第146話 關于死滅回游                    （19P）                                ",
            "chapterId": "/m171792/"
        },
        {
            "chapterTitle": "第145話 裹                    （19P）                                ",
            "chapterId": "/m170760/"
        },
        {
            "chapterTitle": "第144話 那個地方                    （19P）                                ",
            "chapterId": "/m169098/"
        },
        {
            "chapterTitle": "第143話 二次                    （18P）                                ",
            "chapterId": "/m168095/"
        },
        {
            "chapterTitle": "第142話 哥哥的背脊                    （19P）                                ",
            "chapterId": "/m167013/"
        },
        {
            "chapterTitle": "第141話 后面的正面                    （4P）                                ",
            "chapterId": "/m165589/"
        },
        {
            "chapterTitle": "第140話 執行                    （19P）                                ",
            "chapterId": "/m164761/"
        },
        {
            "chapterTitle": "第139話 獵人                    （18P）                                ",
            "chapterId": "/m163705/"
        },
        {
            "chapterTitle": "第138話 禪院家                    （19P）                                ",
            "chapterId": "/m163019/"
        },
        {
            "chapterTitle": "第137話 堅白同異                    （20P）                                ",
            "chapterId": "/m161256/"
        },
        {
            "chapterTitle": "第136話 澀谷事變（53）                    （6P）                                ",
            "chapterId": "/m159037/"
        },
        {
            "chapterTitle": "第135話 澀谷事變（52）                    （8P）                                ",
            "chapterId": "/m158331/"
        },
        {
            "chapterTitle": "第134話 澀谷事變（51）                    （21P）                                ",
            "chapterId": "/m156296/"
        },
        {
            "chapterTitle": "第133話 試看版                    （19P）                                ",
            "chapterId": "/m154244/"
        },
        {
            "chapterTitle": "番外篇                     （6P）                                ",
            "chapterId": "/m152888/"
        },
        {
            "chapterTitle": "第132話 澀谷事變（49）                    （8P）                                ",
            "chapterId": "/m152139/"
        },
        {
            "chapterTitle": "第131話 澀谷事變（48）                    （7P）                                ",
            "chapterId": "/m151113/"
        },
        {
            "chapterTitle": "最速角色書                     （29P）                                ",
            "chapterId": "/m150361/"
        },
        {
            "chapterTitle": "第130話 澀谷事變（47）                    （8P）                                ",
            "chapterId": "/m150138/"
        },
        {
            "chapterTitle": "特別番外篇                     （17P）                                ",
            "chapterId": "/m149555/"
        },
        {
            "chapterTitle": "第129話 澀谷事變（46）                    （7P）                                ",
            "chapterId": "/m148423/"
        },
        {
            "chapterTitle": "第128話 澀谷事變（45）                    （5P）                                ",
            "chapterId": "/m147610/"
        },
        {
            "chapterTitle": "第127話                     （11P）                                ",
            "chapterId": "/m146519/"
        },
        {
            "chapterTitle": "第126話 澀谷事變（43）                    （6P）                                ",
            "chapterId": "/m145403/"
        },
        {
            "chapterTitle": "第125話 那孩子的故事                    （6P）                                ",
            "chapterId": "/m144649/"
        },
        {
            "chapterTitle": "第124話                     （6P）                                ",
            "chapterId": "/m144105/"
        },
        {
            "chapterTitle": "第123話 澀谷事變（41）                    （5P）                                ",
            "chapterId": "/m143065/"
        },
        {
            "chapterTitle": "第122話                     （4P）                                ",
            "chapterId": "/m141421/"
        },
        {
            "chapterTitle": "第121話 澀谷事變（39）                    （6P）                                ",
            "chapterId": "/m140358/"
        },
        {
            "chapterTitle": "第120話 澀谷事變（38）                    （9P）                                ",
            "chapterId": "/m139457/"
        },
        {
            "chapterTitle": "第119話 澀谷事變（37）                    （15P）                                ",
            "chapterId": "/m138489/"
        },
        {
            "chapterTitle": "第118話 澀谷事變（36）                    （6P）                                ",
            "chapterId": "/m137425/"
        },
        {
            "chapterTitle": "12卷附錄                      （16P）                                ",
            "chapterId": "/m135684/"
        },
        {
            "chapterTitle": "第117話 澀谷事變（35）                    （11P）                                ",
            "chapterId": "/m134299/"
        },
        {
            "chapterTitle": "第116話 澀谷事變（34）                    （17P）                                ",
            "chapterId": "/m133010/"
        },
        {
            "chapterTitle": "第115話 澀谷事變（33）                    （6P）                                ",
            "chapterId": "/m131045/"
        },
        {
            "chapterTitle": "第114話 澀谷事變（32）                    （6P）                                ",
            "chapterId": "/m130022/"
        },
        {
            "chapterTitle": "第113話 澀谷事變（31）                    （6P）                                ",
            "chapterId": "/m129181/"
        },
        {
            "chapterTitle": "第112話 澀谷事變（30）                    （4P）                                ",
            "chapterId": "/m127256/"
        },
        {
            "chapterTitle": "第111話 澀谷事變（29）                    （6P）                                ",
            "chapterId": "/m126525/"
        },
        {
            "chapterTitle": "第110話 澀谷事變（28）                    （18P）                                ",
            "chapterId": "/m125441/"
        },
        {
            "chapterTitle": "第109話 澀谷事變（27）                    （20P）                                ",
            "chapterId": "/m124395/"
        },
        {
            "chapterTitle": "11卷附錄                      （15P）                                ",
            "chapterId": "/m124394/"
        },
        {
            "chapterTitle": "第108話 澀谷事變（26）                    （18P）                                ",
            "chapterId": "/m122465/"
        },
        {
            "chapterTitle": "第107話 澀谷事變（25）                    （12P）                                ",
            "chapterId": "/m121198/"
        },
        {
            "chapterTitle": "第106話 澀谷事變（24）                    （6P）                                ",
            "chapterId": "/m120023/"
        },
        {
            "chapterTitle": "第105話 澀谷事變（23）                    （4P）                                ",
            "chapterId": "/m119490/"
        },
        {
            "chapterTitle": "第104話 澀谷事變（22）                    （9P）                                ",
            "chapterId": "/m116275/"
        },
        {
            "chapterTitle": "第103話 澀谷事變（21）                    （20P）                                ",
            "chapterId": "/m114847/"
        },
        {
            "chapterTitle": "第102話 澀谷事變（20）                    （21P）                                ",
            "chapterId": "/m114001/"
        },
        {
            "chapterTitle": "澀谷事變（19）                     （18P）                                ",
            "chapterId": "/m113215/"
        },
        {
            "chapterTitle": "10卷附錄                      （16P）                                ",
            "chapterId": "/m113112/"
        },
        {
            "chapterTitle": "第100話 澀谷事變（18）                    （23P）                                ",
            "chapterId": "/m112698/"
        },
        {
            "chapterTitle": "第99話                     （19P）                                ",
            "chapterId": "/m112235/"
        },
        {
            "chapterTitle": "第98話 澀谷事變（16）                    （21P）                                ",
            "chapterId": "/m109170/"
        },
        {
            "chapterTitle": "第97話 澀谷事變（15）                    （20P）                                ",
            "chapterId": "/m105897/"
        },
        {
            "chapterTitle": "第96話 澀谷事變（14）                    （19P）                                ",
            "chapterId": "/m102760/"
        },
        {
            "chapterTitle": "第95話 澀谷事變（13）                    （21P）                                ",
            "chapterId": "/m102485/"
        },
        {
            "chapterTitle": "第94話 澀谷事變（12）                    （20P）                                ",
            "chapterId": "/m101976/"
        },
        {
            "chapterTitle": "第93話 澀谷事變（11）                    （18P）                                ",
            "chapterId": "/m101975/"
        },
        {
            "chapterTitle": "第92話                     （22P）                                ",
            "chapterId": "/m101134/"
        },
        {
            "chapterTitle": "第91話 澀谷事變（9）                    （21P）                                ",
            "chapterId": "/m94526/"
        },
        {
            "chapterTitle": "第90話 澀谷事變 (8)                    （21P）                                ",
            "chapterId": "/m84662/"
        },
        {
            "chapterTitle": "第85話                     （0P）                                ",
            "chapterId": "/m63057/"
        },
        {
            "chapterTitle": "最速角色書                     （30P）                                ",
            "chapterId": "/m19300/"
        },
        {
            "chapterTitle": "第6卷                     （16P）                                ",
            "chapterId": "/m19299/"
        },
        {
            "chapterTitle": "第5卷                     （22P）                                ",
            "chapterId": "/m19298/"
        },
        {
            "chapterTitle": "第4卷                     （22P）                                ",
            "chapterId": "/m19297/"
        },
        {
            "chapterTitle": "第3卷                     （20P）                                ",
            "chapterId": "/m19296/"
        },
        {
            "chapterTitle": "第2卷                     （20P）                                ",
            "chapterId": "/m19295/"
        },
        {
            "chapterTitle": "第1卷                     （10P）                                ",
            "chapterId": "/m19294/"
        },
        {
            "chapterTitle": "第78話                     （19P）                                ",
            "chapterId": "/m19293/"
        },
        {
            "chapterTitle": "第77話                     （6P）                                ",
            "chapterId": "/m19292/"
        },
        {
            "chapterTitle": "第76話                     （19P）                                ",
            "chapterId": "/m19291/"
        },
        {
            "chapterTitle": "第75話                     （4P）                                ",
            "chapterId": "/m19290/"
        },
        {
            "chapterTitle": "第74話                     （20P）                                ",
            "chapterId": "/m19289/"
        },
        {
            "chapterTitle": "第73話                     （6P）                                ",
            "chapterId": "/m19288/"
        },
        {
            "chapterTitle": "第72話                     （9P）                                ",
            "chapterId": "/m19287/"
        },
        {
            "chapterTitle": "第71話                     （18P）                                ",
            "chapterId": "/m19286/"
        },
        {
            "chapterTitle": "第70話                     （21P）                                ",
            "chapterId": "/m19285/"
        },
        {
            "chapterTitle": "第69話                     （20P）                                ",
            "chapterId": "/m19284/"
        },
        {
            "chapterTitle": "第68話                     （18P）                                ",
            "chapterId": "/m19283/"
        },
        {
            "chapterTitle": "第67話                     （20P）                                ",
            "chapterId": "/m19282/"
        },
        {
            "chapterTitle": "第66話                     （20P）                                ",
            "chapterId": "/m19281/"
        },
        {
            "chapterTitle": "第65話                     （26P）                                ",
            "chapterId": "/m19280/"
        },
        {
            "chapterTitle": "第64話                     （20P）                                ",
            "chapterId": "/m19279/"
        },
        {
            "chapterTitle": "第63話                     （23P）                                ",
            "chapterId": "/m19278/"
        },
        {
            "chapterTitle": "第62話                     （20P）                                ",
            "chapterId": "/m19277/"
        },
        {
            "chapterTitle": "第61話                     （18P）                                ",
            "chapterId": "/m19276/"
        },
        {
            "chapterTitle": "第60話                     （20P）                                ",
            "chapterId": "/m19275/"
        },
        {
            "chapterTitle": "第59話                     （22P）                                ",
            "chapterId": "/m19274/"
        },
        {
            "chapterTitle": "第58話                     （24P）                                ",
            "chapterId": "/m19273/"
        },
        {
            "chapterTitle": "第57話                     （24P）                                ",
            "chapterId": "/m19272/"
        },
        {
            "chapterTitle": "第56話                     （25P）                                ",
            "chapterId": "/m19271/"
        },
        {
            "chapterTitle": "第55話                     （21P）                                ",
            "chapterId": "/m19270/"
        },
        {
            "chapterTitle": "第54話                     （20P）                                ",
            "chapterId": "/m19269/"
        },
        {
            "chapterTitle": "第53話                     （19P）                                ",
            "chapterId": "/m19268/"
        },
        {
            "chapterTitle": "第52話                     （6P）                                ",
            "chapterId": "/m19267/"
        },
        {
            "chapterTitle": "第51話                     （21P）                                ",
            "chapterId": "/m19266/"
        },
        {
            "chapterTitle": "第50話                     （19P）                                ",
            "chapterId": "/m19265/"
        },
        {
            "chapterTitle": "第49話                     （23P）                                ",
            "chapterId": "/m19264/"
        },
        {
            "chapterTitle": "第48話                     （20P）                                ",
            "chapterId": "/m19263/"
        },
        {
            "chapterTitle": "第47話                     （8P）                                ",
            "chapterId": "/m19262/"
        },
        {
            "chapterTitle": "第46話                     （23P）                                ",
            "chapterId": "/m19261/"
        },
        {
            "chapterTitle": "第45話                     （20P）                                ",
            "chapterId": "/m19260/"
        },
        {
            "chapterTitle": "第44話                     （20P）                                ",
            "chapterId": "/m19259/"
        },
        {
            "chapterTitle": "第43話                     （23P）                                ",
            "chapterId": "/m19258/"
        },
        {
            "chapterTitle": "第42話                     （21P）                                ",
            "chapterId": "/m19257/"
        },
        {
            "chapterTitle": "第41話                     （29P）                                ",
            "chapterId": "/m19256/"
        },
        {
            "chapterTitle": "第40話                     （21P）                                ",
            "chapterId": "/m19255/"
        },
        {
            "chapterTitle": "第39話                     （23P）                                ",
            "chapterId": "/m19254/"
        },
        {
            "chapterTitle": "第38話                     （19P）                                ",
            "chapterId": "/m19253/"
        },
        {
            "chapterTitle": "第37話                     （24P）                                ",
            "chapterId": "/m19252/"
        },
        {
            "chapterTitle": "第36話                     （21P）                                ",
            "chapterId": "/m19251/"
        },
        {
            "chapterTitle": "第35話                     （20P）                                ",
            "chapterId": "/m19250/"
        },
        {
            "chapterTitle": "第34話                     （19P）                                ",
            "chapterId": "/m19249/"
        },
        {
            "chapterTitle": "第33話                     （19P）                                ",
            "chapterId": "/m19248/"
        },
        {
            "chapterTitle": "第32話                     （22P）                                ",
            "chapterId": "/m19247/"
        },
        {
            "chapterTitle": "第31話                     （22P）                                ",
            "chapterId": "/m19246/"
        },
        {
            "chapterTitle": "第30話                     （19P）                                ",
            "chapterId": "/m19245/"
        },
        {
            "chapterTitle": "第29話                     （19P）                                ",
            "chapterId": "/m19244/"
        },
        {
            "chapterTitle": "第28話                     （23P）                                ",
            "chapterId": "/m19243/"
        },
        {
            "chapterTitle": "第27話                     （20P）                                ",
            "chapterId": "/m19242/"
        },
        {
            "chapterTitle": "第26話                     （19P）                                ",
            "chapterId": "/m19241/"
        },
        {
            "chapterTitle": "第25話                     （20P）                                ",
            "chapterId": "/m19240/"
        },
        {
            "chapterTitle": "第24話                     （20P）                                ",
            "chapterId": "/m19239/"
        },
        {
            "chapterTitle": "第23話                     （21P）                                ",
            "chapterId": "/m19238/"
        },
        {
            "chapterTitle": "第22話                     （20P）                                ",
            "chapterId": "/m19237/"
        },
        {
            "chapterTitle": "第21話                     （20P）                                ",
            "chapterId": "/m19236/"
        },
        {
            "chapterTitle": "第20話                     （20P）                                ",
            "chapterId": "/m19235/"
        },
        {
            "chapterTitle": "第19話                     （21P）                                ",
            "chapterId": "/m19234/"
        },
        {
            "chapterTitle": "第18話                     （20P）                                ",
            "chapterId": "/m19233/"
        },
        {
            "chapterTitle": "第17話                     （20P）                                ",
            "chapterId": "/m19232/"
        },
        {
            "chapterTitle": "第16話                     （22P）                                ",
            "chapterId": "/m19231/"
        },
        {
            "chapterTitle": "第15話                     （17P）                                ",
            "chapterId": "/m19230/"
        },
        {
            "chapterTitle": "第14話                     （19P）                                ",
            "chapterId": "/m19229/"
        },
        {
            "chapterTitle": "第13話                     （18P）                                ",
            "chapterId": "/m19228/"
        },
        {
            "chapterTitle": "第12話                     （19P）                                ",
            "chapterId": "/m19227/"
        },
        {
            "chapterTitle": "第11話                     （19P）                                ",
            "chapterId": "/m19226/"
        },
        {
            "chapterTitle": "第10話                     （19P）                                ",
            "chapterId": "/m19225/"
        },
        {
            "chapterTitle": "第9話                     （19P）                                ",
            "chapterId": "/m19224/"
        },
        {
            "chapterTitle": "第8話                     （18P）                                ",
            "chapterId": "/m19223/"
        },
        {
            "chapterTitle": "第7話                     （18P）                                ",
            "chapterId": "/m19222/"
        },
        {
            "chapterTitle": "第6話                     （18P）                                ",
            "chapterId": "/m19221/"
        },
        {
            "chapterTitle": "第5話                     （19P）                                ",
            "chapterId": "/m19220/"
        },
        {
            "chapterTitle": "第4話                     （19P）                                ",
            "chapterId": "/m19219/"
        },
        {
            "chapterTitle": "第3話                     （22P）                                ",
            "chapterId": "/m19218/"
        },
        {
            "chapterTitle": "第2話                     （25P）                                ",
            "chapterId": "/m19217/"
        },
        {
            "chapterTitle": "第1話                     （52P）                                ",
            "chapterId": "/m19216/"
        }
    ]
}